setup.py
django_rest_swagger_docstring/__init__.py
django_rest_swagger_docstring/parsers.py
django_rest_swagger_docstring/schemas.py
django_rest_swagger_docstring/urls.py
django_rest_swagger_docstring/views.py
django_rest_swagger_docstring.egg-info/PKG-INFO
django_rest_swagger_docstring.egg-info/SOURCES.txt
django_rest_swagger_docstring.egg-info/dependency_links.txt
django_rest_swagger_docstring.egg-info/requires.txt
django_rest_swagger_docstring.egg-info/top_level.txt