Metadata-Version: 1.1
Name: django-rest-swagger-docstring
Version: 0.2.1
Summary: Supports docstrings in Django Rest Swagger for versions >2.0
Home-page: https://github.com/johniak/django-rest-swagger-docstring
Author: Jan Romaniak
Author-email: romaniakjan@gmail.com
License: MIT License
Platform: UNKNOWN
Classifier: Environment :: Web Environment
Classifier: Framework :: Django
Classifier: Intended Audience :: Developers
Classifier: License :: OSI Approved :: MIT License
Classifier: Operating System :: OS Independent
Classifier: Programming Language :: Python
Classifier: Programming Language :: Python :: 2.7
Classifier: Programming Language :: Python :: 3.5
Classifier: Programming Language :: Python :: 3.6
Classifier: Topic :: Internet :: WWW/HTTP
Classifier: Topic :: Internet :: WWW/HTTP :: Dynamic Content
